{
  "pattern": {
    "panels": {
      "right_btorso": {
        "translation": [
          0.0,
          96.08960403366139,
          -25.0
        ],
        "rotation": [
          -0.0,
          0.0,
          0.0
        ],
        "vertices": [
          [
            0,
            0
          ],
          [
            -20.77434,
            0
          ],
          [
            -22.070889956390644,
            20.083532199904663
          ],
          [
            -16.518316722003185,
            38.26221219990467
          ],
          [
            -13.415315000000001,
            39.44744388057066
          ],
          [
            0.0,
            35.754900030876726
          ]
        ],
        "edges": [
          {
            "endpoints": [
              0,
              1
            ]
          },
          {
            "endpoints": [
              1,
              2
            ]
          },
          {
            "endpoints": [
              2,
              3
            ],
            "label": "right_armhole",
            "curvature": {
              "type": "cubic",
              "params": [
                [
                  0.19999999999999996,
                  -0.35
                ],
                [
                  0.5,
                  -0.2
                ]
              ]
            }
          },
          {
            "endpoints": [
              3,
              4
            ]
          },
          {
            "endpoints": [
              4,
              5
            ],
            "label": "right_collar",
            "curvature": {
              "type": "circle",
              "params": [
                26.21574238680788,
                0,
                1
              ]
            }
          },
          {
            "endpoints": [
              5,
              0
            ]
          }
        ],
        "label": "body"
      },
      "right_ftorso": {
        "translation": [
          0.0,
          96.08960403366139,
          30.0
        ],
        "rotation": [
          -0.0,
          0.0,
          0.0
        ],
        "vertices": [
          [
            0,
            0
          ],
          [
            0.0,
            21.364689055020964
          ],
          [
            -13.415315,
            39.447443827061065
          ],
          [
            -16.609968505008418,
            38.227205091623674
          ],
          [
            -24.535761308018834,
            20.04852509162367
          ],
          [
            -23.05908,
            0
          ]
        ],
        "edges": [
          {
            "endpoints": [
              0,
              1
            ]
          },
          {
            "endpoints": [
              1,
              2
            ],
            "label": "right_collar"
          },
          {
            "endpoints": [
              2,
              3
            ]
          },
          {
            "endpoints": [
              3,
              4
            ],
            "label": "right_armhole",
            "curvature": {
              "type": "cubic",
              "params": [
                [
                  0.5,
                  0.2
                ],
                [
                  0.8,
                  0.35
                ]
              ]
            }
          },
          {
            "endpoints": [
              4,
              5
            ]
          },
          {
            "endpoints": [
              5,
              0
            ]
          }
        ],
        "label": "body"
      },
      "left_ftorso": {
        "translation": [
          0.0,
          96.08960403366139,
          30.0
        ],
        "rotation": [
          -0.0,
          0.0,
          0.0
        ],
        "vertices": [
          [
            0.0,
            0.0
          ],
          [
            23.05908,
            0.0
          ],
          [
            24.535761308018834,
            20.04852509162367
          ],
          [
            16.609968505008418,
            38.227205091623674
          ],
          [
            13.415315,
            39.447443827061065
          ],
          [
            0.0,
            21.364689055020964
          ]
        ],
        "edges": [
          {
            "endpoints": [
              0,
              1
            ]
          },
          {
            "endpoints": [
              1,
              2
            ]
          },
          {
            "endpoints": [
              2,
              3
            ],
            "label": "left_armhole",
            "curvature": {
              "type": "cubic",
              "params": [
                [
                  0.19999999999999996,
                  0.35
                ],
                [
                  0.5,
                  0.2
                ]
              ]
            }
          },
          {
            "endpoints": [
              3,
              4
            ]
          },
          {
            "endpoints": [
              4,
              5
            ],
            "label": "left_collar"
          },
          {
            "endpoints": [
              5,
              0
            ]
          }
        ],
        "label": "body"
      },
      "left_btorso": {
        "translation": [
          0.0,
          96.08960403366139,
          -25.0
        ],
        "rotation": [
          -0.0,
          0.0,
          0.0
        ],
        "vertices": [
          [
            0.0,
            0.0
          ],
          [
            0.0,
            35.754900030876726
          ],
          [
            13.415315000000001,
            39.44744388057066
          ],
          [
            16.518316722003185,
            38.26221219990467
          ],
          [
            22.070889956390644,
            20.083532199904663
          ],
          [
            20.77434,
            0.0
          ]
        ],
        "edges": [
          {
            "endpoints": [
              0,
              1
            ]
          },
          {
            "endpoints": [
              1,
              2
            ],
            "label": "left_collar",
            "curvature": {
              "type": "circle",
              "params": [
                26.21574238680788,
                0,
                1
              ]
            }
          },
          {
            "endpoints": [
              2,
              3
            ]
          },
          {
            "endpoints": [
              3,
              4
            ],
            "label": "left_armhole",
            "curvature": {
              "type": "cubic",
              "params": [
                [
                  0.5,
                  -0.2
                ],
                [
                  0.8,
                  -0.35
                ]
              ]
            }
          },
          {
            "endpoints": [
              4,
              5
            ]
          },
          {
            "endpoints": [
              5,
              0
            ]
          }
        ],
        "label": "body"
      },
      "wb_front": {
        "translation": [
          -21.28475,
          100.90629999999999,
          20.0
        ],
        "rotation": [
          -0.0,
          0.0,
          0.0
        ],
        "vertices": [
          [
            0,
            0
          ],
          [
            13.178750217701202,
            0.0
          ],
          [
            29.3907501490132,
            0.0
          ],
          [
            42.5695,
            0
          ],
          [
            42.5695,
            4.52618
          ],
          [
            0,
            4.52618
          ]
        ],
        "edges": [
          {
            "endpoints": [
              0,
              1
            ]
          },
          {
            "endpoints": [
              1,
              2
            ]
          },
          {
            "endpoints": [
              2,
              3
            ]
          },
          {
            "endpoints": [
              3,
              4
            ]
          },
          {
            "endpoints": [
              4,
              5
            ],
            "label": "lower_interface"
          },
          {
            "endpoints": [
              5,
              0
            ]
          }
        ],
        "label": "body"
      },
      "wb_back": {
        "translation": [
          -18.88735,
          100.90629999999999,
          -15.0
        ],
        "rotation": [
          -0.0,
          0.0,
          0.0
        ],
        "vertices": [
          [
            0,
            0
          ],
          [
            0,
            4.52618
          ],
          [
            37.7747,
            4.52618
          ],
          [
            37.7747,
            0
          ],
          [
            29.931537575643624,
            0.0
          ],
          [
            25.513862477693934,
            0.0
          ],
          [
            12.26083769840012,
            0.0
          ],
          [
            7.8431627532303825,
            0.0
          ]
        ],
        "edges": [
          {
            "endpoints": [
              0,
              1
            ]
          },
          {
            "endpoints": [
              1,
              2
            ],
            "label": "lower_interface"
          },
          {
            "endpoints": [
              2,
              3
            ]
          },
          {
            "endpoints": [
              3,
              4
            ]
          },
          {
            "endpoints": [
              4,
              5
            ]
          },
          {
            "endpoints": [
              5,
              6
            ]
          },
          {
            "endpoints": [
              6,
              7
            ]
          },
          {
            "endpoints": [
              7,
              0
            ]
          }
        ],
        "label": "body"
      },
      "skirt_front": {
        "translation": [
          -24.839399999999998,
          48.527007499999996,
          25.0
        ],
        "rotation": [
          -0.0,
          0.0,
          0.0
        ],
        "vertices": [
          [
            0.0,
            0.0
          ],
          [
            48.41219999999999,
            0.0
          ],
          [
            48.41219999999999,
            24.682619999999996
          ],
          [
            45.89807210729599,
            47.31352
          ],
          [
            32.7193222563092,
            47.31352
          ],
          [
            32.515711202661194,
            29.20994497137009
          ],
          [
            32.3121001490132,
            47.31352
          ],
          [
            16.100100217701197,
            47.31352
          ],
          [
            15.896489164053197,
            29.20994497137009
          ],
          [
            15.6928781104052,
            47.31352
          ],
          [
            2.5141278927040034,
            47.31352
          ],
          [
            0,
            24.682619999999996
          ]
        ],
        "edges": [
          {
            "endpoints": [
              0,
              1
            ]
          },
          {
            "endpoints": [
              1,
              2
            ]
          },
          {
            "endpoints": [
              2,
              3
            ],
            "curvature": {
              "type": "quadratic",
              "params": [
                [
                  0.49780663507196266,
                  -0.05530267598097362
                ]
              ]
            }
          },
          {
            "endpoints": [
              3,
              4
            ]
          },
          {
            "endpoints": [
              4,
              5
            ]
          },
          {
            "endpoints": [
              5,
              6
            ]
          },
          {
            "endpoints": [
              6,
              7
            ]
          },
          {
            "endpoints": [
              7,
              8
            ]
          },
          {
            "endpoints": [
              8,
              9
            ]
          },
          {
            "endpoints": [
              9,
              10
            ]
          },
          {
            "endpoints": [
              10,
              11
            ],
            "curvature": {
              "type": "quadratic",
              "params": [
                [
                  0.502193368674214,
                  -0.055302675718639636
                ]
              ]
            }
          },
          {
            "endpoints": [
              11,
              0
            ]
          }
        ],
        "label": "leg"
      },
      "skirt_back": {
        "translation": [
          -27.839399999999998,
          47.527007499999996,
          -20.0
        ],
        "rotation": [
          -0.0,
          0.0,
          0.0
        ],
        "vertices": [
          [
            0.0,
            0.0
          ],
          [
            0,
            24.682619999999996
          ],
          [
            2.639834287339202,
            48.445065
          ],
          [
            10.48299704056959,
            48.445065
          ],
          [
            12.06105096873479,
            30.18208687487913
          ],
          [
            13.639104896899989,
            48.445065
          ],
          [
            18.05677984206972,
            48.445065
          ],
          [
            19.63483377023492,
            28.138479122607848
          ],
          [
            21.212887698400117,
            48.445065
          ],
          [
            34.465912477693934,
            48.445065
          ],
          [
            36.04396640585914,
            28.138479122607848
          ],
          [
            37.622020334024334,
            48.445065
          ],
          [
            42.03969543197402,
            48.445065
          ],
          [
            43.617749360139214,
            30.18208687487913
          ],
          [
            45.19580328830442,
            48.445065
          ],
          [
            53.0389657126608,
            48.445065
          ],
          [
            55.6788,
            24.682619999999996
          ],
          [
            55.6788,
            0.0
          ]
        ],
        "edges": [
          {
            "endpoints": [
              0,
              1
            ]
          },
          {
            "endpoints": [
              1,
              2
            ],
            "curvature": {
              "type": "quadratic",
              "params": [
                [
                  0.49780663132577274,
                  0.055302675718637166
                ]
              ]
            }
          },
          {
            "endpoints": [
              2,
              3
            ]
          },
          {
            "endpoints": [
              3,
              4
            ]
          },
          {
            "endpoints": [
              4,
              5
            ]
          },
          {
            "endpoints": [
              5,
              6
            ]
          },
          {
            "endpoints": [
              6,
              7
            ]
          },
          {
            "endpoints": [
              7,
              8
            ]
          },
          {
            "endpoints": [
              8,
              9
            ]
          },
          {
            "endpoints": [
              9,
              10
            ]
          },
          {
            "endpoints": [
              10,
              11
            ]
          },
          {
            "endpoints": [
              11,
              12
            ]
          },
          {
            "endpoints": [
              12,
              13
            ]
          },
          {
            "endpoints": [
              13,
              14
            ]
          },
          {
            "endpoints": [
              14,
              15
            ]
          },
          {
            "endpoints": [
              15,
              16
            ],
            "curvature": {
              "type": "quadratic",
              "params": [
                [
                  0.5021933647801559,
                  0.05530267599740243
                ]
              ]
            }
          },
          {
            "endpoints": [
              16,
              17
            ]
          },
          {
            "endpoints": [
              17,
              0
            ]
          }
        ],
        "label": "leg"
      }
    },
    "stitches": [
      [
        {
          "panel": "right_ftorso",
          "edge": 2
        },
        {
          "panel": "right_btorso",
          "edge": 3
        }
      ],
      [
        {
          "panel": "right_ftorso",
          "edge": 4
        },
        {
          "panel": "right_btorso",
          "edge": 1
        }
      ],
      [
        {
          "panel": "left_ftorso",
          "edge": 3
        },
        {
          "panel": "left_btorso",
          "edge": 2
        }
      ],
      [
        {
          "panel": "left_ftorso",
          "edge": 1
        },
        {
          "panel": "left_btorso",
          "edge": 4
        }
      ],
      [
        {
          "panel": "right_ftorso",
          "edge": 0
        },
        {
          "panel": "left_ftorso",
          "edge": 5
        }
      ],
      [
        {
          "panel": "right_btorso",
          "edge": 5
        },
        {
          "panel": "left_btorso",
          "edge": 0
        }
      ],
      [
        {
          "panel": "wb_front",
          "edge": 5
        },
        {
          "panel": "wb_back",
          "edge": 0
        }
      ],
      [
        {
          "panel": "wb_front",
          "edge": 3
        },
        {
          "panel": "wb_back",
          "edge": 2
        }
      ],
      [
        {
          "panel": "skirt_front",
          "edge": 8
        },
        {
          "panel": "skirt_front",
          "edge": 7
        }
      ],
      [
        {
          "panel": "skirt_front",
          "edge": 5
        },
        {
          "panel": "skirt_front",
          "edge": 4
        }
      ],
      [
        {
          "panel": "skirt_back",
          "edge": 3
        },
        {
          "panel": "skirt_back",
          "edge": 4
        }
      ],
      [
        {
          "panel": "skirt_back",
          "edge": 6
        },
        {
          "panel": "skirt_back",
          "edge": 7
        }
      ],
      [
        {
          "panel": "skirt_back",
          "edge": 9
        },
        {
          "panel": "skirt_back",
          "edge": 10
        }
      ],
      [
        {
          "panel": "skirt_back",
          "edge": 12
        },
        {
          "panel": "skirt_back",
          "edge": 13
        }
      ],
      [
        {
          "panel": "skirt_front",
          "edge": 11
        },
        {
          "panel": "skirt_back",
          "edge": 0
        }
      ],
      [
        {
          "panel": "skirt_front",
          "edge": 10
        },
        {
          "panel": "skirt_back",
          "edge": 1
        }
      ],
      [
        {
          "panel": "skirt_front",
          "edge": 2
        },
        {
          "panel": "skirt_back",
          "edge": 15
        }
      ],
      [
        {
          "panel": "skirt_front",
          "edge": 1
        },
        {
          "panel": "skirt_back",
          "edge": 16
        }
      ],
      [
        {
          "panel": "wb_front",
          "edge": 0
        },
        {
          "panel": "skirt_front",
          "edge": 9
        }
      ],
      [
        {
          "panel": "wb_front",
          "edge": 1
        },
        {
          "panel": "skirt_front",
          "edge": 6
        }
      ],
      [
        {
          "panel": "wb_front",
          "edge": 2
        },
        {
          "panel": "skirt_front",
          "edge": 3
        }
      ],
      [
        {
          "panel": "wb_back",
          "edge": 3
        },
        {
          "panel": "skirt_back",
          "edge": 14
        }
      ],
      [
        {
          "panel": "wb_back",
          "edge": 4
        },
        {
          "panel": "skirt_back",
          "edge": 11
        }
      ],
      [
        {
          "panel": "wb_back",
          "edge": 5
        },
        {
          "panel": "skirt_back",
          "edge": 8
        }
      ],
      [
        {
          "panel": "wb_back",
          "edge": 6
        },
        {
          "panel": "skirt_back",
          "edge": 5
        }
      ],
      [
        {
          "panel": "wb_back",
          "edge": 7
        },
        {
          "panel": "skirt_back",
          "edge": 2
        }
      ]
    ],
    "panel_order": [
      "right_btorso",
      "right_ftorso",
      "skirt_back",
      "wb_back",
      "wb_front",
      "skirt_front",
      "left_btorso",
      "left_ftorso"
    ]
  },
  "parameters": {},
  "parameter_order": [],
  "properties": {
    "curvature_coords": "relative",
    "normalize_panel_translation": false,
    "normalized_edge_loops": true,
    "units_in_meter": 100
  }
}